{
  "ts": "2026-06-04T05:37:42.965Z",
  "results": {
    "imperial": {
      "ok": true,
      "data": {
        "blackjack_minor": "3 422 €",
        "blackjack_major": "29 045 €",
        "ultimate": "22 001 €"
      }
    },
    "barriere": {
      "ok": true,
      "data": {
        "blackjack_minor": "13 790 €",
        "blackjack_major": "84 525 €",
        "ultimate": "6 791 €"
      }
    },
    "elyseesclub": {
      "ok": true,
      "data": {
        "blackjack": "29 879 €",
        "ultimate": "13 047 €"
      }
    },
    "circus": {
      "ok": true,
      "data": {
        "uth_progressive": "66 077 €",
        "blazing_blackjack": "7 181 €"
      }
    },
    "pierrecharron": {
      "ok": true,
      "data": {
        "blackjack_minor": "2 506 €",
        "blackjack_major": "11 208 €",
        "ultimate": "38 088 €"
      }
    },
    "montmartre": {
      "ok": true,
      "data": {
        "mega_blackjack": "14 762 €",
        "mega_ultimate": "58 680 €",
        "minor": "13 377 €"
      }
    }
  }
}