{
  "ts": "2026-07-07T18:37:57.468Z",
  "results": {
    "pasino": {
      "ok": true,
      "data": {
        "ultimate": null,
        "blackjack_major": "21 620 €",
        "blackjack_minor": "5 143 €"
      }
    },
    "imperial": {
      "ok": true,
      "data": {
        "blackjack_minor": "2 315 €",
        "blackjack_major": "8 079 €",
        "ultimate": "41 368 €"
      }
    },
    "barriere": {
      "ok": true,
      "data": {
        "ultimate": null,
        "blackjack_major": "128 342 €",
        "blackjack_minor": null
      }
    },
    "elyseesclub": {
      "ok": true,
      "data": {
        "blackjack": "10 279 €",
        "ultimate": "87 845 €"
      }
    },
    "circus": {
      "ok": true,
      "data": {
        "uth_progressive": "30 272 €",
        "blazing_blackjack": "18 191 €"
      }
    },
    "pierrecharron": {
      "ok": true,
      "data": {
        "blackjack_minor": "3 277 €",
        "blackjack_major": "11 774 €",
        "ultimate": "10 507 €"
      }
    },
    "montmartre": {
      "ok": true,
      "data": {
        "mega_ultimate": "154 848 €",
        "mega_blackjack": "29 117 €",
        "minor": "1 797 €"
      }
    }
  }
}