{
  "ts": "2026-06-01T03:50:30.919Z",
  "results": {
    "imperial": {
      "ok": true,
      "data": {
        "blackjack_minor": "1 770 €",
        "blackjack_major": "27 228 €",
        "ultimate": "16 831 €"
      }
    },
    "barriere": {
      "ok": true,
      "data": {
        "blackjack_minor": "9 562 €",
        "blackjack_major": "79 874 €",
        "ultimate": "27 980 €"
      }
    },
    "elyseesclub": {
      "ok": true,
      "data": {
        "blackjack": "29 275 €",
        "ultimate": "11 431 €"
      }
    },
    "circus": {
      "ok": true,
      "data": {
        "uth_progressive": "58 305 €",
        "blazing_blackjack": "5 597 €"
      }
    },
    "pierrecharron": {
      "ok": true,
      "data": {
        "blackjack_minor": "7 590 €",
        "blackjack_major": "9 246 €",
        "ultimate": "28 268 €"
      }
    },
    "montmartre": {
      "ok": true,
      "data": {
        "mega_blackjack": "66 124 €",
        "mega_ultimate": "54 759 €",
        "minor": "12 389 €"
      }
    }
  }
}