{
  "ts": "2026-07-08T21:06:09.193Z",
  "results": {
    "pasino": {
      "ok": true,
      "data": {
        "ultimate": null,
        "blackjack_major": "22 746 €",
        "blackjack_minor": "6 167 €"
      }
    },
    "imperial": {
      "ok": true,
      "data": {
        "blackjack_minor": "2 754 €",
        "blackjack_major": "8 562 €",
        "ultimate": "42 749 €"
      }
    },
    "barriere": {
      "ok": true,
      "data": {
        "ultimate": null,
        "blackjack_major": "128 342 €",
        "blackjack_minor": null
      }
    },
    "elyseesclub": {
      "ok": true,
      "data": {
        "blackjack": "10 279 €",
        "ultimate": "87 845 €"
      }
    },
    "circus": {
      "ok": true,
      "data": {
        "uth_progressive": "31 284 €",
        "blazing_blackjack": "19 069 €"
      }
    },
    "pierrecharron": {
      "ok": true,
      "data": {
        "blackjack_minor": "3 902 €",
        "blackjack_major": "12 461 €",
        "ultimate": "12 373 €"
      }
    },
    "montmartre": {
      "ok": true,
      "data": {
        "mega_ultimate": "159 621 €",
        "mega_blackjack": "29 680 €",
        "minor": "2 309 €"
      }
    }
  }
}