{
  "ts": "2026-06-02T19:00:22.990Z",
  "results": {
    "imperial": {
      "ok": true,
      "data": {
        "blackjack_minor": "2 521 €",
        "blackjack_major": "28 054 €",
        "ultimate": "19 597 €"
      }
    },
    "barriere": {
      "ok": true,
      "data": {
        "blackjack_minor": "12 293 €",
        "blackjack_major": "82 878 €",
        "ultimate": "34 424 €"
      }
    },
    "elyseesclub": {
      "ok": true,
      "data": {
        "blackjack": "29 789 €",
        "ultimate": "12 435 €"
      }
    },
    "circus": {
      "ok": true,
      "data": {
        "uth_progressive": "61 162 €",
        "blazing_blackjack": "6 033 €"
      }
    },
    "pierrecharron": {
      "ok": true,
      "data": {
        "blackjack_minor": "8 409 €",
        "blackjack_major": "10 147 €",
        "ultimate": "32 737 €"
      }
    },
    "montmartre": {
      "ok": true,
      "data": {
        "mega_blackjack": "14 220 €",
        "mega_ultimate": "55 792 €",
        "minor": "12 884 €"
      }
    }
  }
}